diviner/__init__.py
diviner/exceptions.py
diviner/grouped_pmdarima.py
diviner/grouped_prophet.py
diviner/version.py
diviner/analysis/__init__.py
diviner/analysis/pmdarima_analyzer.py
diviner/config/__init__.py
diviner/config/grouped_prophet/__init__.py
diviner/config/grouped_prophet/prophet_config.py
diviner/config/grouped_prophet/utils/__init__.py
diviner/config/grouped_prophet/utils/prophet_config_utils.py
diviner/data/__init__.py
diviner/data/base_group_generator.py
diviner/data/pandas_group_generator.py
diviner/data/utils/__init__.py
diviner/data/utils/dataframe_utils.py
diviner/model/__init__.py
diviner/model/base_model.py
diviner/scoring/__init__.py
diviner/scoring/pmdarima_cross_validate.py
diviner/scoring/prophet_cross_validate.py
diviner/serialize/__init__.py
diviner/serialize/pmdarima_serializer.py
diviner/utils/__init__.py
diviner/utils/annotators.py
diviner/utils/common.py
diviner/utils/pmdarima_utils.py
diviner/utils/prophet_utils.py
diviner/utils/example_utils/__init__.py
diviner/utils/example_utils/example_data_generator.py
examples/__init__.py
examples/grouped_pmdarima/__init__.py
examples/grouped_pmdarima/grouped_pmdarima_analyze_differencing_terms_and_apply.py
examples/grouped_pmdarima/grouped_pmdarima_arima_example.py
examples/grouped_pmdarima/grouped_pmdarima_autoarima_example.py
examples/grouped_pmdarima/grouped_pmdarima_pipeline_example.py
examples/grouped_pmdarima/grouped_pmdarima_series_exploration.py
examples/grouped_pmdarima/grouped_pmdarima_subset_prediction_example.py
examples/grouped_prophet/__init__.py
examples/grouped_prophet/grouped_prophet_example.py
examples/grouped_prophet/grouped_prophet_subset_prediction_example.py
diviner-0.1.1.dist-info/LICENSE
diviner-0.1.1.dist-info/METADATA
diviner-0.1.1.dist-info/NOTICE
diviner-0.1.1.dist-info/WHEEL
diviner-0.1.1.dist-info/top_level.txt
diviner-0.1.1.dist-info/RECORD
