Metadata-Version: 2.1
Name: diviner
Version: 0.1.1
Summary: Diviner: A Grouped Forecasting API
Home-page: https://github.com/databricks/diviner
Author: Databricks
Author-email: benjamin.wilson@databricks.com
License: Apache2.0
Project-URL: Issue Tracker, https://github.com/databricks/diviner/issues
Project-URL: Documentation, https://databricks-diviner.readthedocs.io/en/latest/
Keywords: ml ai forecasting databricks
Platform: UNKNOWN
Classifier: Intended Audience :: Developers
Classifier: Intended Audience :: End Users/Desktop
Classifier: Operating System :: OS Independent
Classifier: Programming Language :: Python :: 3.7
Classifier: Programming Language :: Python :: 3.8
Classifier: Programming Language :: Python :: 3.9
Classifier: Programming Language :: Python :: 3 :: Only
Classifier: Development Status :: 3 - Alpha
Requires-Python: >=3.7
License-File: LICENSE
License-File: NOTICE
Requires-Dist: numpy
Requires-Dist: pandas
Requires-Dist: prophet
Requires-Dist: pmdarima
Requires-Dist: packaging
